weixin/__init__.py
weixin/client.py
weixin/dotdict.py
aioweixin-0.0.1.dist-info/METADATA
aioweixin-0.0.1.dist-info/WHEEL
aioweixin-0.0.1.dist-info/top_level.txt
aioweixin-0.0.1.dist-info/RECORD
